afs_scenario/__init__.py
afs_scenario/__main__.py
afs_scenario/create.py
afs_scenario/init.py
afs_scenario/main.py
afs_scenario/setup.py
afs_scenario/util.py
afs_scenario/cookiecutter/drivers/cookiecutter.json
afs_scenario/cookiecutter/drivers/{{cookiecutter.molecule_directory}}/__drivers__/delegated/README.md
afs_scenario/cookiecutter/drivers/{{cookiecutter.molecule_directory}}/__drivers__/delegated/cleanup.yml
afs_scenario/cookiecutter/drivers/{{cookiecutter.molecule_directory}}/__drivers__/delegated/create.yml
afs_scenario/cookiecutter/drivers/{{cookiecutter.molecule_directory}}/__drivers__/delegated/destroy.yml
afs_scenario/cookiecutter/drivers/{{cookiecutter.molecule_directory}}/__drivers__/delegated/prepare.yml.j2
afs_scenario/cookiecutter/drivers/{{cookiecutter.molecule_directory}}/__drivers__/delegated/library/virt_up.py
afs_scenario/cookiecutter/drivers/{{cookiecutter.molecule_directory}}/__drivers__/vagrant/README.md
afs_scenario/cookiecutter/drivers/{{cookiecutter.molecule_directory}}/__drivers__/vagrant/prepare.yml.j2
afs_scenario/cookiecutter/scenario/cookiecutter.json
afs_scenario/cookiecutter/scenario/{{cookiecutter.scenario_name}}/converge.yml
afs_scenario/cookiecutter/scenario/{{cookiecutter.scenario_name}}/molecule.yml.j2
afs_scenario/cookiecutter/scenario/{{cookiecutter.scenario_name}}/verify.yml
afs_scenario-1.0.0.dist-info/METADATA
afs_scenario-1.0.0.dist-info/WHEEL
afs_scenario-1.0.0.dist-info/entry_points.txt
afs_scenario-1.0.0.dist-info/top_level.txt
afs_scenario-1.0.0.dist-info/RECORD
