Metadata-Version: 2.1
Name: afs-scenario
Version: 1.0.0
Summary: Create templated molecule scenarios for openafs_contrib.openafs playbooks and roles.
Home-page: https://github.com/openafs-contrib/ansible-openafs/tree/master/tools/afs_scenario
Author: Michael Meffie
Author-email: mmeffie@sinenomine.net
License: UNKNOWN
Platform: UNKNOWN
Classifier: Programming Language :: Python :: 3
Classifier: License :: OSI Approved :: MIT License
Classifier: Operating System :: OS Independent
Requires-Python: >=3.6
Requires-Dist: Click
Requires-Dist: cookiecutter
Requires-Dist: jinja2-ansible-filters
Requires-Dist: pyyaml
